[
  {
   "elements": [
	{"type": "component",
	 "title": "Component",
	 "menu":"us-component-menu",
	 "icon": "./dm/icons/us/es/component/Component.png"
	},
	{"type": "interface",
	 "title": "Interface",
	 "lable":"true",
	 "menu":"us-component-menu",
	 "icon": "./dm/icons/us/es/component/Interface.png"
	},
	{"type": "port",
	 "title": "Port",
	 "menu":"us-component-menu",
	 "icon": "./dm/icons/us/es/component/Port.png"
	},
	{"type": "empty",
	 "title": "Empty",
	 "menu":"us-component-menu",
	 "hidden": true
	},
	{"type": "instance",
	 "title": "Instance Specification",
	 "menu":"us-component-menu",
	 "icon": "./dm/icons/us/es/component/InstanceSpecification.png"
	},
	{"type": "note",
	 "title": "Note",
	 "menu": "us-note-menu",
	 "icon": "./dm/icons/us/es/common/Note.png"
	}
    ],
    "connectors": [
      {"connector":"dependency",
	   "title":"Dependency",
	   "icon": "./dm/icons/us/cs/dependency.png"
	  },
      {"connector":"arc",
	   "title":"Interface Observer",
	   "icon": "./dm/icons/us/cs/interface_required.png"
	  },
      {"connector":"realization",
	   "title":"Realization",
	   "icon": "./dm/icons/us/cs/realization.png"
	  },
      {"connector":"association",
	   "title":"Association",
	   "icon": "./dm/icons/us/cs/association.png"
	  },
      {"connector":"aggregation",
	   "title":"Aggregation",
	   "icon": "./dm/icons/us/cs/aggregation.png"
	  },
      {"connector":"composition",
	   "title":"Composition",
	   "icon": "./dm/icons/us/cs/composition.png"
	  },
      {"connector":"anchor",
	   "title":"Anchor",
	   "icon": "./dm/icons/us/cs/AnchorToNote.png"
	  },
      {"connector":"anchor",
	   "title":"Constraint",
	   "icon": "./dm/icons/us/cs/Constrain.png"
	  },
      {"connector":"nested",
	   "title":"Containment",
	   "icon": "./dm/icons/us/cs/nested.png"
	  }
    ],
    "menus": [
	  {"id":"us-note-menu",
	   "items": [
				{"el":"Note",
				 "cs":[
						{"connector":"anchor",
						 "icon":"dm/icons/us/cs/diagram/anchor_with_note.gif"}
					  ]
				}
			 ]
	  },
	  {"id":"us-component-menu",
	   "items": [
				{"el":"Component",
				 "cs":[
						{"connector":"association",
						 "icon":"dm/icons/us/cs/association.png"
						},
						{"connector":"aggregation",
						 "icon":"dm/icons/us/cs/aggregation.png"
						},
						{"connector":"composition",
						 "icon":"dm/icons/us/cs/composition.png"
						},
						{"connector":"iobserver",
						 "icon":"dm/icons/us/cs/composition.png"
						}
					  ]
				},
				{"el":"Interface",
				 "cs":[
						{"connector":"realization",
						 "icon":"dm/icons/us/cs/interface.png"
						}
					  ]
				},
				{"el":"Empty",
				 "cs":[
                        {"connector":"arc",
						 "icon":"dm/icons/us/cs/interface_required.png"
						}
					  ]
				},
				{"el":"Port",
				 "cs":[
						{"connector":"association",
						 "icon":"dm/icons/us/cs/association.gif"
						}
					  ]
				},
				{"el":"Note",
				 "cs":[
						{"connector":"anchor",
						 "icon":"dm/icons/us/cs/diagram/anchor_with_note.gif"}
					  ]
				}
			 ]
	  }
	]
   }
]
